README.md
setup.py
ai_cloud_sdk_4pd/__init__.py
ai_cloud_sdk_4pd/client.py
ai_cloud_sdk_4pd/models.py
ai_cloud_sdk_4pd.egg-info/PKG-INFO
ai_cloud_sdk_4pd.egg-info/SOURCES.txt
ai_cloud_sdk_4pd.egg-info/dependency_links.txt
ai_cloud_sdk_4pd.egg-info/requires.txt
ai_cloud_sdk_4pd.egg-info/top_level.txt
mock/__init__.py
mock/mock_async_asr.py
tests/test.py
tests/test_asr.py
tests/test_asr_direct_vi.py
tests/test_asr_single.py
tests/test_chat.py
tests/test_detection.py
tests/test_mid_translate.py
tests/test_translate.py
tests/test_tts.py