Metadata-Version: 2.1
Name: ai_cloud_sdk_4pd
Version: 0.3.8
Summary: 4paradigm AI Cloud Service SDK Library for Python
Home-page: https://gitlab.4pd.io/ai_clound_platform/4pd-ai-clound-sdk
Author: 4paradigm AI Cloud SDK
Author-email: 
Keywords: 4pd_ai_cloud
Platform: any
Classifier: Intended Audience :: Developers
Classifier: Programming Language :: Python
Classifier: Programming Language :: Python :: 3
Classifier: Programming Language :: Python :: 3.6
Classifier: Programming Language :: Python :: 3.7
Classifier: Programming Language :: Python :: 3.8
Classifier: Programming Language :: Python :: 3.9
Classifier: Topic :: Software Development
Requires-Python: >=3.6
Requires-Dist: requests
